nex5file/__init__.py
nex5file/filedata.py
nex5file/headers.py
nex5file/reader.py
nex5file/variables.py
nex5file/writer.py
nex5file-0.1.3.dist-info/LICENSE
nex5file-0.1.3.dist-info/METADATA
nex5file-0.1.3.dist-info/WHEEL
nex5file-0.1.3.dist-info/top_level.txt
nex5file-0.1.3.dist-info/RECORD
