Metadata-Version: 2.1
Name: nex5file
Version: 0.1.3
Summary: Read and write .nex and .nex5 files and edit data stored in .nex and .nex5 files.
Author-email: Alex Kirillov <alex@neuroexplorer.com>
Project-URL: homepage, https://github.com/NeuroExplorer/nex5file
Project-URL: documentation, https://www.neuroexplorer.com/nex5file/
Project-URL: repository, https://github.com/NeuroExplorer/nex5file
Keywords: NeuroExplorer,nex,nex5,.nex,.nex5
Classifier: Programming Language :: Python :: 3
Classifier: License :: OSI Approved :: MIT License
Classifier: Operating System :: OS Independent
Requires-Python: >=3.7
License-File: LICENSE
Requires-Dist: numpy
